tracardi_sentiment_analysis/plugin.py
tracardi_sentiment_analysis/model/configuration.py
tracardi_sentiment_analysis/model/sa_source_onfiguration.py
tracardi_sentiment_analysis/model/__pycache__/configuration.cpython-38.pyc
tracardi_sentiment_analysis/model/__pycache__/sa_source_onfiguration.cpython-38.pyc
tracardi_sentiment_analysis/test/manual_test.py
tracardi_sentiment_analysis-0.6.2.dist-info/LICENSE.md
tracardi_sentiment_analysis-0.6.2.dist-info/METADATA
tracardi_sentiment_analysis-0.6.2.dist-info/WHEEL
tracardi_sentiment_analysis-0.6.2.dist-info/top_level.txt
tracardi_sentiment_analysis-0.6.2.dist-info/RECORD
